{
  "project_info": {
    "project_number": "338586420553",
    "project_id": "mapapp-a0ad8",
    "storage_bucket": "mapapp-a0ad8.appspot.com"
  },
  "client": [
    {
      "client_info": {
        "mobilesdk_app_id": "1:338586420553:android:ab7dc37b7b4266dc4cc698",
        "android_client_info": {
          "package_name": "com.abrebostudio.haritaapp"
        }
      },
      "oauth_client": [],
      "api_key": [
        {
          "current_key": "AIzaSyCiQcauTBTpAkVAEom8yHmQFYapaB12T6U"
        }
      ],
      "services": {
        "appinvite_service": {
          "other_platform_oauth_client": []
        }
      }
    }
  ],
  "configuration_version": "1"
}